[{"id":"https://openalex.org/C2778096292","name":"Design engineer","level":2,"works_count":179,"children_count":0},{"id":"https://openalex.org/C558441949","name":"Lifting equipment","level":2,"works_count":451,"children_count":0},{"id":"https://openalex.org/C18762648","name":"Work (physics)","level":2,"works_count":2243531,"children_count":11,"_concept_file":"concept-18762648.json"},{"id":"https://openalex.org/C188198153","name":"Limiting","level":2,"works_count":206696,"children_count":0},{"id":"https://openalex.org/C107706546","name":"Heat exchanger","level":2,"works_count":202137,"children_count":17,"_concept_file":"concept-107706546.json"},{"id":"https://openalex.org/C200457457","name":"Ventilation (architecture)","level":2,"works_count":163584,"children_count":2,"_concept_file":"concept-200457457.json"},{"id":"https://openalex.org/C523214423","name":"Machining","level":2,"works_count":178570,"children_count":13,"_concept_file":"concept-523214423.json"},{"id":"https://openalex.org/C115901376","name":"Automation","level":2,"works_count":202709,"children_count":5,"_concept_file":"concept-115901376.json"},{"id":"https://openalex.org/C43521106","name":"Pipeline (software)","level":2,"works_count":157943,"children_count":2,"_concept_file":"concept-43521106.json"},{"id":"https://openalex.org/C2780428219","name":"Cover (algebra)","level":2,"works_count":493690,"children_count":2,"_concept_file":"concept-2780428219.json"},{"id":"https://openalex.org/C25197100","name":"Drilling","level":2,"works_count":159498,"children_count":20,"_concept_file":"concept-25197100.json"},{"id":"https://openalex.org/C2778712887","name":"Spring (device)","level":2,"works_count":201236,"children_count":0},{"id":"https://openalex.org/C529865628","name":"Manifold (fluid mechanics)","level":2,"works_count":85499,"children_count":0},{"id":"https://openalex.org/C2777551076","name":"Front (military)","level":2,"works_count":529657,"children_count":1,"_concept_file":"concept-2777551076.json"},{"id":"https://openalex.org/C89992363","name":"Track (disk drive)","level":2,"works_count":132851,"children_count":3,"_concept_file":"concept-89992363.json"},{"id":"https://openalex.org/C2777655017","name":"Toolbox","level":2,"works_count":38355,"children_count":0},{"id":"https://openalex.org/C103742991","name":"Air conditioning","level":2,"works_count":75662,"children_count":10,"_concept_file":"concept-103742991.json"},{"id":"https://openalex.org/C116067010","name":"Airflow","level":2,"works_count":60981,"children_count":1,"_concept_file":"concept-116067010.json"},{"id":"https://openalex.org/C111106434","name":"Die (integrated circuit)","level":2,"works_count":226794,"children_count":0},{"id":"https://openalex.org/C2775922551","name":"Parallels","level":2,"works_count":48709,"children_count":1,"_concept_file":"concept-2775922551.json"},{"id":"https://openalex.org/C69907114","name":"Refrigeration","level":2,"works_count":45009,"children_count":1,"_concept_file":"concept-69907114.json"},{"id":"https://openalex.org/C41325743","name":"Pressure sensor","level":2,"works_count":34464,"children_count":2,"_concept_file":"concept-41325743.json"},{"id":"https://openalex.org/C10390562","name":"Spline (mechanical)","level":2,"works_count":30854,"children_count":0},{"id":"https://openalex.org/C91914117","name":"Coolant","level":2,"works_count":50959,"children_count":2,"_concept_file":"concept-91914117.json"},{"id":"https://openalex.org/C138101251","name":"Thread (computing)","level":2,"works_count":45109,"children_count":2,"_concept_file":"concept-138101251.json"},{"id":"https://openalex.org/C23795335","name":"Suction","level":2,"works_count":46824,"children_count":1,"_concept_file":"concept-23795335.json"},{"id":"https://openalex.org/C171635847","name":"Micrometer","level":2,"works_count":17852,"children_count":0},{"id":"https://openalex.org/C67953723","name":"Workstation","level":2,"works_count":32618,"children_count":0},{"id":"https://openalex.org/C155911762","name":"Blueprint","level":2,"works_count":31811,"children_count":0},{"id":"https://openalex.org/C53942344","name":"Fold (higher-order function)","level":2,"works_count":26077,"children_count":0},{"id":"https://openalex.org/C100784341","name":"Eccentric","level":2,"works_count":19866,"children_count":2,"_concept_file":"concept-100784341.json"},{"id":"https://openalex.org/C2779301550","name":"Working fluid","level":2,"works_count":18603,"children_count":0},{"id":"https://openalex.org/C153005164","name":"Impeller","level":2,"works_count":43221,"children_count":4,"_concept_file":"concept-153005164.json"},{"id":"https://openalex.org/C135186712","name":"Injector","level":2,"works_count":42553,"children_count":0},{"id":"https://openalex.org/C5941749","name":"Machine tool","level":2,"works_count":34136,"children_count":0},{"id":"https://openalex.org/C2779472054","name":"Groove (engineering)","level":2,"works_count":29076,"children_count":0},{"id":"https://openalex.org/C2779268580","name":"Allowance (engineering)","level":2,"works_count":27578,"children_count":0},{"id":"https://openalex.org/C173736775","name":"Drill","level":2,"works_count":44686,"children_count":5,"_concept_file":"concept-173736775.json"},{"id":"https://openalex.org/C105289051","name":"Pillar","level":2,"works_count":34073,"children_count":0},{"id":"https://openalex.org/C2777852167","name":"Nail (fastener)","level":2,"works_count":30811,"children_count":1,"_concept_file":"concept-2777852167.json"},{"id":"https://openalex.org/C2987684023","name":"Gas turbines","level":2,"works_count":43372,"children_count":2,"_concept_file":"concept-2987684023.json"},{"id":"https://openalex.org/C114834414","name":"Thermal management of electronic devices and systems","level":2,"works_count":18575,"children_count":1,"_concept_file":"concept-114834414.json"},{"id":"https://openalex.org/C2779793219","name":"Brace","level":2,"works_count":25398,"children_count":1,"_concept_file":"concept-2779793219.json"},{"id":"https://openalex.org/C2780383046","name":"Cutting tool","level":2,"works_count":13699,"children_count":0},{"id":"https://openalex.org/C96494537","name":"Forging","level":2,"works_count":41605,"children_count":1,"_concept_file":"concept-96494537.json"},{"id":"https://openalex.org/C192097918","name":"Scrap","level":2,"works_count":20040,"children_count":0},{"id":"https://openalex.org/C2778571141","name":"Syringe","level":2,"works_count":15532,"children_count":2,"_concept_file":"concept-2778571141.json"},{"id":"https://openalex.org/C75403996","name":"Garbage","level":2,"works_count":21951,"children_count":1,"_concept_file":"concept-75403996.json"},{"id":"https://openalex.org/C2778091609","name":"Mount","level":2,"works_count":41690,"children_count":0},{"id":"https://openalex.org/C119823426","name":"Computer Aided Design","level":2,"works_count":20321,"children_count":0},{"id":"https://openalex.org/C2776937656","name":"Nesting (process)","level":2,"works_count":15753,"children_count":0},{"id":"https://openalex.org/C24090081","name":"Preventive maintenance","level":2,"works_count":18568,"children_count":2,"_concept_file":"concept-24090081.json"},{"id":"https://openalex.org/C134949993","name":"Pencil (optics)","level":2,"works_count":15304,"children_count":0},{"id":"https://openalex.org/C80264047","name":"Pressure measurement","level":2,"works_count":17562,"children_count":0},{"id":"https://openalex.org/C2994254730","name":"Internal rotation","level":2,"works_count":7850,"children_count":0},{"id":"https://openalex.org/C56951928","name":"Trimming","level":2,"works_count":10230,"children_count":0},{"id":"https://openalex.org/C173991790","name":"Evaporative cooler","level":2,"works_count":11126,"children_count":0},{"id":"https://openalex.org/C30905978","name":"Metering mode","level":2,"works_count":20503,"children_count":0},{"id":"https://openalex.org/C129727815","name":"Axle","level":2,"works_count":26374,"children_count":3,"_concept_file":"concept-129727815.json"},{"id":"https://openalex.org/C14480152","name":"Pinch","level":2,"works_count":16734,"children_count":1,"_concept_file":"concept-14480152.json"},{"id":"https://openalex.org/C164915370","name":"Cooling capacity","level":2,"works_count":10346,"children_count":0},{"id":"https://openalex.org/C107524782","name":"Lever","level":2,"works_count":14339,"children_count":0},{"id":"https://openalex.org/C163114375","name":"Surface engineering","level":2,"works_count":3752,"children_count":0},{"id":"https://openalex.org/C27134321","name":"Stirling engine","level":2,"works_count":15439,"children_count":1,"_concept_file":"concept-27134321.json"},{"id":"https://openalex.org/C2780644530","name":"Splash","level":2,"works_count":8057,"children_count":1,"_concept_file":"concept-2780644530.json"},{"id":"https://openalex.org/C11394606","name":"Hydraulic machinery","level":2,"works_count":32988,"children_count":1,"_concept_file":"concept-11394606.json"},{"id":"https://openalex.org/C13655849","name":"Hammer","level":2,"works_count":21078,"children_count":0},{"id":"https://openalex.org/C146778888","name":"Installation","level":2,"works_count":23379,"children_count":0},{"id":"https://openalex.org/C2777154459","name":"Heating system","level":2,"works_count":12302,"children_count":0},{"id":"https://openalex.org/C125209513","name":"Doors","level":2,"works_count":25542,"children_count":0},{"id":"https://openalex.org/C2781424646","name":"SWORD","level":2,"works_count":18916,"children_count":0},{"id":"https://openalex.org/C99527880","name":"Universal design","level":2,"works_count":11108,"children_count":1,"_concept_file":"concept-99527880.json"},{"id":"https://openalex.org/C14794904","name":"Steam turbine","level":2,"works_count":24534,"children_count":1,"_concept_file":"concept-14794904.json"},{"id":"https://openalex.org/C125557594","name":"Refrigerator car","level":2,"works_count":14240,"children_count":1,"_concept_file":"concept-125557594.json"},{"id":"https://openalex.org/C133769200","name":"Bracket","level":2,"works_count":12421,"children_count":1,"_concept_file":"concept-133769200.json"},{"id":"https://openalex.org/C2778844933","name":"Interlocking","level":2,"works_count":11714,"children_count":0},{"id":"https://openalex.org/C16629374","name":"Storage tank","level":2,"works_count":14746,"children_count":1,"_concept_file":"concept-16629374.json"},{"id":"https://openalex.org/C2779538338","name":"Completion (oil and gas wells)","level":2,"works_count":22663,"children_count":0},{"id":"https://openalex.org/C53016008","name":"Front and back ends","level":2,"works_count":14257,"children_count":0},{"id":"https://openalex.org/C175503448","name":"Thermodynamic cycle","level":2,"works_count":5575,"children_count":0},{"id":"https://openalex.org/C3019666875","name":"Assembly line","level":2,"works_count":7784,"children_count":0},{"id":"https://openalex.org/C2992734406","name":"One shot","level":2,"works_count":7145,"children_count":0},{"id":"https://openalex.org/C2777020290","name":"Boss","level":2,"works_count":11630,"children_count":0},{"id":"https://openalex.org/C2776871301","name":"Shutter","level":2,"works_count":8751,"children_count":1,"_concept_file":"concept-2776871301.json"},{"id":"https://openalex.org/C2988879937","name":"Fluid pressure","level":2,"works_count":4776,"children_count":0},{"id":"https://openalex.org/C2780727963","name":"Computer-aided","level":2,"works_count":10191,"children_count":0},{"id":"https://openalex.org/C76272257","name":"Micropump","level":2,"works_count":4140,"children_count":1,"_concept_file":"concept-76272257.json"},{"id":"https://openalex.org/C1934278","name":"Compressed air","level":2,"works_count":10010,"children_count":0},{"id":"https://openalex.org/C128871136","name":"Pressure head","level":2,"works_count":2636,"children_count":0},{"id":"https://openalex.org/C154750914","name":"Motor drive","level":2,"works_count":6471,"children_count":0},{"id":"https://openalex.org/C40523978","name":"Fork (system call)","level":2,"works_count":9646,"children_count":0},{"id":"https://openalex.org/C144444463","name":"Stamping","level":2,"works_count":10179,"children_count":0},{"id":"https://openalex.org/C111808769","name":"Inclined plane","level":2,"works_count":4694,"children_count":0},{"id":"https://openalex.org/C171937826","name":"Pulley","level":2,"works_count":8152,"children_count":1,"_concept_file":"concept-171937826.json"},{"id":"https://openalex.org/C2984377249","name":"3d printer","level":2,"works_count":6474,"children_count":0},{"id":"https://openalex.org/C66098623","name":"Inflatable","level":2,"works_count":8502,"children_count":0},{"id":"https://openalex.org/C130614165","name":"Tripod (photography)","level":2,"works_count":4253,"children_count":0},{"id":"https://openalex.org/C94870803","name":"Butt joint","level":2,"works_count":5626,"children_count":0},{"id":"https://openalex.org/C31954730","name":"Compressed natural gas","level":2,"works_count":5524,"children_count":0},{"id":"https://openalex.org/C2985847231","name":"Production cost","level":2,"works_count":8707,"children_count":0},{"id":"https://openalex.org/C2778240408","name":"Fastener","level":2,"works_count":7031,"children_count":0},{"id":"https://openalex.org/C48431260","name":"Hydraulic cylinder","level":2,"works_count":10937,"children_count":1,"_concept_file":"concept-48431260.json"},{"id":"https://openalex.org/C2780424376","name":"Wellhead","level":2,"works_count":8932,"children_count":0},{"id":"https://openalex.org/C40336117","name":"Plenum space","level":2,"works_count":10612,"children_count":0},{"id":"https://openalex.org/C23725684","name":"Maintenance engineering","level":2,"works_count":6846,"children_count":0},{"id":"https://openalex.org/C4846943","name":"Cryocooler","level":2,"works_count":6670,"children_count":1,"_concept_file":"concept-4846943.json"},{"id":"https://openalex.org/C83404686","name":"Warm front","level":2,"works_count":3041,"children_count":0},{"id":"https://openalex.org/C169961218","name":"Notching","level":2,"works_count":2794,"children_count":0},{"id":"https://openalex.org/C32520587","name":"Tractive force","level":2,"works_count":3862,"children_count":0},{"id":"https://openalex.org/C134519083","name":"Peristaltic pump","level":2,"works_count":3963,"children_count":0},{"id":"https://openalex.org/C29302406","name":"Wrench","level":2,"works_count":4041,"children_count":0},{"id":"https://openalex.org/C62420388","name":"Draft tube","level":2,"works_count":3794,"children_count":0},{"id":"https://openalex.org/C87864170","name":"Unit cost","level":2,"works_count":3739,"children_count":0},{"id":"https://openalex.org/C2780146601","name":"Ladle","level":2,"works_count":6829,"children_count":0},{"id":"https://openalex.org/C2777511293","name":"Coordinate-measuring machine","level":2,"works_count":4615,"children_count":0},{"id":"https://openalex.org/C2993360226","name":"Oil supply","level":2,"works_count":3090,"children_count":0},{"id":"https://openalex.org/C65120314","name":"Hydraulic pump","level":2,"works_count":7385,"children_count":0},{"id":"https://openalex.org/C5379308","name":"Glovebox","level":2,"works_count":3495,"children_count":0},{"id":"https://openalex.org/C2779606619","name":"Interchangeability","level":2,"works_count":3951,"children_count":0},{"id":"https://openalex.org/C3019953569","name":"Dual purpose","level":2,"works_count":6905,"children_count":0},{"id":"https://openalex.org/C2780991453","name":"Virtual prototyping","level":2,"works_count":5673,"children_count":0},{"id":"https://openalex.org/C55975022","name":"Variable displacement pump","level":2,"works_count":5941,"children_count":0},{"id":"https://openalex.org/C2985681428","name":"Mechanical design","level":2,"works_count":3162,"children_count":0},{"id":"https://openalex.org/C28961703","name":"Friction loss","level":2,"works_count":2038,"children_count":0},{"id":"https://openalex.org/C62926433","name":"Bevel gear","level":2,"works_count":4791,"children_count":0},{"id":"https://openalex.org/C2778295731","name":"Water hammer","level":2,"works_count":4798,"children_count":0},{"id":"https://openalex.org/C19117948","name":"Applied mechanics","level":2,"works_count":2260,"children_count":0},{"id":"https://openalex.org/C2992072310","name":"Spur gear","level":2,"works_count":3876,"children_count":0},{"id":"https://openalex.org/C109661024","name":"Vertical plane","level":2,"works_count":2467,"children_count":0},{"id":"https://openalex.org/C150011116","name":"Footplate","level":2,"works_count":2069,"children_count":0},{"id":"https://openalex.org/C2992097611","name":"Waste material","level":2,"works_count":3728,"children_count":0},{"id":"https://openalex.org/C4402595","name":"Planned maintenance","level":2,"works_count":4495,"children_count":0},{"id":"https://openalex.org/C198340109","name":"Crusher","level":2,"works_count":5939,"children_count":0},{"id":"https://openalex.org/C2985438705","name":"Aero engine","level":2,"works_count":5012,"children_count":0},{"id":"https://openalex.org/C2778502540","name":"Test fixture","level":2,"works_count":3055,"children_count":0},{"id":"https://openalex.org/C113603800","name":"Control rod","level":2,"works_count":6222,"children_count":0},{"id":"https://openalex.org/C3018081369","name":"New energy","level":2,"works_count":2648,"children_count":0},{"id":"https://openalex.org/C2778181360","name":"Surgical instrument","level":2,"works_count":2460,"children_count":0},{"id":"https://openalex.org/C2991818253","name":"Gear tooth","level":2,"works_count":2651,"children_count":0},{"id":"https://openalex.org/C2776043813","name":"Batch production","level":2,"works_count":1913,"children_count":0},{"id":"https://openalex.org/C155908867","name":"Carton","level":2,"works_count":4425,"children_count":0},{"id":"https://openalex.org/C2992285028","name":"Work time","level":2,"works_count":1925,"children_count":0},{"id":"https://openalex.org/C2779041774","name":"Loader","level":2,"works_count":5889,"children_count":0},{"id":"https://openalex.org/C134535237","name":"Industrial design","level":2,"works_count":4335,"children_count":0},{"id":"https://openalex.org/C3017909875","name":"Working environment","level":2,"works_count":4690,"children_count":0},{"id":"https://openalex.org/C2985276286","name":"Bilateral symmetry","level":2,"works_count":1090,"children_count":0},{"id":"https://openalex.org/C2776377115","name":"Steam engine","level":2,"works_count":3178,"children_count":0},{"id":"https://openalex.org/C2777305511","name":"Centring","level":2,"works_count":1548,"children_count":0},{"id":"https://openalex.org/C3017515162","name":"Lateral wall","level":2,"works_count":1288,"children_count":0},{"id":"https://openalex.org/C2985318046","name":"Rolling mill","level":2,"works_count":7800,"children_count":0},{"id":"https://openalex.org/C44013972","name":"Oil analysis","level":2,"works_count":2762,"children_count":0},{"id":"https://openalex.org/C19221803","name":"Hydraulic accumulator","level":2,"works_count":2759,"children_count":0},{"id":"https://openalex.org/C172644405","name":"Screw thread","level":2,"works_count":2201,"children_count":0},{"id":"https://openalex.org/C33451869","name":"Workover","level":2,"works_count":5013,"children_count":0},{"id":"https://openalex.org/C30207505","name":"Air dryer","level":2,"works_count":903,"children_count":0},{"id":"https://openalex.org/C2987619373","name":"Tunnel boring machine","level":2,"works_count":1270,"children_count":0},{"id":"https://openalex.org/C132643394","name":"Positive displacement meter","level":2,"works_count":3341,"children_count":0},{"id":"https://openalex.org/C116168119","name":"Winch","level":2,"works_count":4490,"children_count":0},{"id":"https://openalex.org/C29450929","name":"Hydraulic motor","level":2,"works_count":4967,"children_count":0},{"id":"https://openalex.org/C78500136","name":"Scraper site","level":2,"works_count":3914,"children_count":0},{"id":"https://openalex.org/C2992525074","name":"Push and pull","level":2,"works_count":634,"children_count":0},{"id":"https://openalex.org/C2778579903","name":"Washer","level":2,"works_count":4157,"children_count":0},{"id":"https://openalex.org/C3020572553","name":"Labor cost","level":2,"works_count":1999,"children_count":0},{"id":"https://openalex.org/C2779671548","name":"Interurban","level":2,"works_count":1802,"children_count":0},{"id":"https://openalex.org/C2982969694","name":"Production efficiency","level":2,"works_count":2676,"children_count":0},{"id":"https://openalex.org/C2778163807","name":"Reamer","level":2,"works_count":1720,"children_count":0},{"id":"https://openalex.org/C2780101202","name":"sports equipment","level":2,"works_count":2392,"children_count":0},{"id":"https://openalex.org/C2780668260","name":"Operating table","level":2,"works_count":1332,"children_count":0},{"id":"https://openalex.org/C149499870","name":"Hoist (device)","level":2,"works_count":5100,"children_count":0},{"id":"https://openalex.org/C2984967376","name":"Machine design","level":2,"works_count":2637,"children_count":0},{"id":"https://openalex.org/C2776715399","name":"Honing","level":2,"works_count":2416,"children_count":0},{"id":"https://openalex.org/C139993351","name":"Electrohydraulic servo valve","level":2,"works_count":3426,"children_count":0},{"id":"https://openalex.org/C10159599","name":"Drive shaft","level":2,"works_count":3248,"children_count":0},{"id":"https://openalex.org/C3802195","name":"Fluid power","level":2,"works_count":3126,"children_count":0},{"id":"https://openalex.org/C2776427868","name":"Forced-air","level":2,"works_count":860,"children_count":0},{"id":"https://openalex.org/C2994134389","name":"Paper production","level":2,"works_count":1443,"children_count":0},{"id":"https://openalex.org/C2994359068","name":"Hydraulic pressure","level":2,"works_count":4076,"children_count":0},{"id":"https://openalex.org/C2776819259","name":"Aspirator","level":2,"works_count":1590,"children_count":0},{"id":"https://openalex.org/C2989418100","name":"Heat energy","level":2,"works_count":3664,"children_count":0},{"id":"https://openalex.org/C2781323245","name":"Hang","level":2,"works_count":4398,"children_count":0},{"id":"https://openalex.org/C129212681","name":"Gear pump","level":2,"works_count":2575,"children_count":0},{"id":"https://openalex.org/C3019831412","name":"Fully automatic","level":2,"works_count":945,"children_count":0},{"id":"https://openalex.org/C2781188742","name":"Crate","level":2,"works_count":1425,"children_count":0},{"id":"https://openalex.org/C2993130303","name":"Electrical machinery","level":2,"works_count":1318,"children_count":0},{"id":"https://openalex.org/C2994418228","name":"Gas pipeline","level":2,"works_count":4567,"children_count":0},{"id":"https://openalex.org/C2777380305","name":"Pneumatics","level":2,"works_count":1979,"children_count":0},{"id":"https://openalex.org/C2776810017","name":"Tine","level":2,"works_count":3233,"children_count":0},{"id":"https://openalex.org/C2986817828","name":"Stepper motor","level":2,"works_count":5502,"children_count":0},{"id":"https://openalex.org/C181204875","name":"Plasma cutting","level":2,"works_count":1634,"children_count":0},{"id":"https://openalex.org/C2781358709","name":"Vacuum pump","level":2,"works_count":2599,"children_count":0},{"id":"https://openalex.org/C2778358062","name":"Lateral movement","level":2,"works_count":601,"children_count":0},{"id":"https://openalex.org/C115534355","name":"JAR","level":2,"works_count":5129,"children_count":0},{"id":"https://openalex.org/C2986611964","name":"Belt conveyor","level":2,"works_count":4098,"children_count":0},{"id":"https://openalex.org/C83604417","name":"Broaching","level":2,"works_count":1604,"children_count":0},{"id":"https://openalex.org/C123935176","name":"Safety valve","level":2,"works_count":3515,"children_count":0},{"id":"https://openalex.org/C2777466363","name":"Design tool","level":2,"works_count":736,"children_count":0},{"id":"https://openalex.org/C103578843","name":"Pneumatic flow control","level":2,"works_count":1082,"children_count":0},{"id":"https://openalex.org/C70816948","name":"Whirlwind","level":2,"works_count":1528,"children_count":0},{"id":"https://openalex.org/C3018717917","name":"Roller coaster","level":2,"works_count":1710,"children_count":0},{"id":"https://openalex.org/C2994236244","name":"Oil storage","level":2,"works_count":1895,"children_count":0},{"id":"https://openalex.org/C2780273575","name":"Expansion chamber","level":2,"works_count":1041,"children_count":0},{"id":"https://openalex.org/C2994193204","name":"Air purification","level":2,"works_count":712,"children_count":0},{"id":"https://openalex.org/C63316402","name":"Universal joint","level":2,"works_count":1027,"children_count":0},{"id":"https://openalex.org/C2777036741","name":"Shackle","level":2,"works_count":972,"children_count":0},{"id":"https://openalex.org/C2779585191","name":"Counterweight","level":2,"works_count":1426,"children_count":0},{"id":"https://openalex.org/C2779427698","name":"SCOOP","level":2,"works_count":4787,"children_count":0},{"id":"https://openalex.org/C118817141","name":"Sprocket","level":2,"works_count":1997,"children_count":0},{"id":"https://openalex.org/C2780052225","name":"Hydraulic press","level":2,"works_count":2061,"children_count":0},{"id":"https://openalex.org/C61097968","name":"Run-out","level":2,"works_count":489,"children_count":0},{"id":"https://openalex.org/C25009002","name":"Radial Force Variation","level":2,"works_count":673,"children_count":0},{"id":"https://openalex.org/C2778646709","name":"Hydraulic circuit","level":2,"works_count":1512,"children_count":0},{"id":"https://openalex.org/C2993805951","name":"Contact system","level":2,"works_count":564,"children_count":0},{"id":"https://openalex.org/C199149936","name":"Pressure system","level":2,"works_count":693,"children_count":0},{"id":"https://openalex.org/C3020631254","name":"Metal working","level":2,"works_count":1205,"children_count":0},{"id":"https://openalex.org/C2777007513","name":"Critical design","level":2,"works_count":414,"children_count":0},{"id":"https://openalex.org/C2778918656","name":"Dust collector","level":2,"works_count":982,"children_count":0},{"id":"https://openalex.org/C2776981007","name":"Oil pump","level":2,"works_count":2533,"children_count":0},{"id":"https://openalex.org/C2986741362","name":"Electronic product","level":2,"works_count":861,"children_count":0},{"id":"https://openalex.org/C2780658917","name":"Support surface","level":2,"works_count":188,"children_count":0},{"id":"https://openalex.org/C2992895212","name":"Sewing machine","level":2,"works_count":1284,"children_count":0},{"id":"https://openalex.org/C2993333825","name":"Hand held","level":2,"works_count":393,"children_count":0},{"id":"https://openalex.org/C538814206","name":"Computer-aided engineering","level":2,"works_count":632,"children_count":0},{"id":"https://openalex.org/C2775884927","name":"Design history","level":2,"works_count":679,"children_count":0},{"id":"https://openalex.org/C2780914392","name":"Babbitt","level":2,"works_count":1198,"children_count":0},{"id":"https://openalex.org/C2994324010","name":"Oil tank","level":2,"works_count":1573,"children_count":0},{"id":"https://openalex.org/C44357349","name":"Telescopic cylinder","level":2,"works_count":1491,"children_count":0},{"id":"https://openalex.org/C164004088","name":"Level sensor","level":2,"works_count":325,"children_count":0},{"id":"https://openalex.org/C86203231","name":"Fluid coupling","level":2,"works_count":532,"children_count":0},{"id":"https://openalex.org/C2780576639","name":"Air current","level":2,"works_count":390,"children_count":0},{"id":"https://openalex.org/C3017741341","name":"Semi automatic","level":2,"works_count":620,"children_count":0},{"id":"https://openalex.org/C2992855926","name":"Deep hole","level":2,"works_count":844,"children_count":0},{"id":"https://openalex.org/C2776439729","name":"Engine room","level":2,"works_count":885,"children_count":0},{"id":"https://openalex.org/C2991964656","name":"Work space","level":2,"works_count":298,"children_count":0},{"id":"https://openalex.org/C2992113537","name":"Machine building","level":2,"works_count":971,"children_count":0}]