[{"id":"https://openalex.org/C2781026528","name":"Meningitis","level":2,"works_count":73177,"children_count":2,"_concept_file":"concept-2781026528.json"},{"id":"https://openalex.org/C3020294031","name":"Breast feeding","level":2,"works_count":39550,"children_count":3,"_concept_file":"concept-3020294031.json"},{"id":"https://openalex.org/C2777091541","name":"Neonatal intensive care unit","level":2,"works_count":40246,"children_count":1,"_concept_file":"concept-2777091541.json"},{"id":"https://openalex.org/C2987955292","name":"Sudden infant death syndrome","level":2,"works_count":8024,"children_count":0},{"id":"https://openalex.org/C2993801374","name":"Acute gastroenteritis","level":2,"works_count":7366,"children_count":0},{"id":"https://openalex.org/C2780610425","name":"Enuresis","level":2,"works_count":9284,"children_count":0},{"id":"https://openalex.org/C3017960651","name":"Sick child","level":2,"works_count":10098,"children_count":0},{"id":"https://openalex.org/C2779651244","name":"Croup","level":2,"works_count":3444,"children_count":0},{"id":"https://openalex.org/C2991856797","name":"Childhood leukaemia","level":2,"works_count":1656,"children_count":0},{"id":"https://openalex.org/C2779746230","name":"Pediatric Neurology","level":2,"works_count":2947,"children_count":0},{"id":"https://openalex.org/C2909602630","name":"Genetic syndromes","level":2,"works_count":1467,"children_count":0},{"id":"https://openalex.org/C2910452277","name":"Altered Mental Status","level":2,"works_count":1934,"children_count":0},{"id":"https://openalex.org/C2780159726","name":"Short course","level":2,"works_count":3887,"children_count":0},{"id":"https://openalex.org/C2909113481","name":"Premature newborn","level":2,"works_count":3092,"children_count":0},{"id":"https://openalex.org/C3020552793","name":"Pediatric hospital","level":2,"works_count":1462,"children_count":0},{"id":"https://openalex.org/C3019691859","name":"Against medical advice","level":2,"works_count":957,"children_count":0},{"id":"https://openalex.org/C2908585274","name":"Poor Feeding","level":2,"works_count":398,"children_count":0},{"id":"https://openalex.org/C2910448334","name":"Neurological problems","level":2,"works_count":383,"children_count":0}]