[{"id":"https://openalex.org/C2780446828","name":"Incarnation","level":2,"works_count":10457,"children_count":0},{"id":"https://openalex.org/C2776265386","name":"Rappaport","level":2,"works_count":1758,"children_count":0},{"id":"https://openalex.org/C2777362836","name":"Righteousness","level":2,"works_count":5038,"children_count":0},{"id":"https://openalex.org/C2777004151","name":"Flannery","level":2,"works_count":3409,"children_count":0},{"id":"https://openalex.org/C2778459489","name":"Repentance","level":2,"works_count":4145,"children_count":0},{"id":"https://openalex.org/C2775858633","name":"Atonement","level":2,"works_count":3918,"children_count":0},{"id":"https://openalex.org/C3018345308","name":"Martin luther","level":2,"works_count":3749,"children_count":0},{"id":"https://openalex.org/C2781307008","name":"Sanctification","level":2,"works_count":2225,"children_count":0},{"id":"https://openalex.org/C2776995859","name":"Body of Christ","level":2,"works_count":2493,"children_count":0},{"id":"https://openalex.org/C2779028768","name":"Agape","level":2,"works_count":1313,"children_count":0},{"id":"https://openalex.org/C2776277238","name":"Dagger","level":2,"works_count":1807,"children_count":0},{"id":"https://openalex.org/C124667768","name":"Pneumatology","level":2,"works_count":1891,"children_count":0},{"id":"https://openalex.org/C2780690153","name":"Moral theology","level":2,"works_count":1228,"children_count":0}]