[{"id":"https://openalex.org/C29122968","name":"Incentive","level":2,"works_count":366806,"children_count":29,"_concept_file":"concept-29122968.json"},{"id":"https://openalex.org/C2781127519","name":"Monopoly","level":2,"works_count":97129,"children_count":8,"_concept_file":"concept-2781127519.json"},{"id":"https://openalex.org/C109747225","name":"Scarcity","level":2,"works_count":52799,"children_count":0},{"id":"https://openalex.org/C2778869765","name":"Inefficiency","level":2,"works_count":35812,"children_count":1,"_concept_file":"concept-2778869765.json"},{"id":"https://openalex.org/C106866004","name":"Economic rent","level":2,"works_count":21976,"children_count":0},{"id":"https://openalex.org/C195534400","name":"Factor market","level":2,"works_count":7849,"children_count":2,"_concept_file":"concept-195534400.json"},{"id":"https://openalex.org/C3018006300","name":"Consumer demand","level":2,"works_count":6975,"children_count":0},{"id":"https://openalex.org/C2985380958","name":"Market competition","level":2,"works_count":6554,"children_count":1,"_concept_file":"concept-2985380958.json"},{"id":"https://openalex.org/C2776838236","name":"Creative destruction","level":2,"works_count":1777,"children_count":0},{"id":"https://openalex.org/C109332788","name":"Economic efficiency","level":2,"works_count":5727,"children_count":0},{"id":"https://openalex.org/C3020225985","name":"State owned","level":2,"works_count":9865,"children_count":0},{"id":"https://openalex.org/C2994191172","name":"Public ownership","level":2,"works_count":3040,"children_count":0},{"id":"https://openalex.org/C138021795","name":"Austrian School","level":2,"works_count":2274,"children_count":0},{"id":"https://openalex.org/C165942954","name":"Commoditization","level":2,"works_count":1450,"children_count":0},{"id":"https://openalex.org/C45622825","name":"Factor price","level":2,"works_count":1611,"children_count":0},{"id":"https://openalex.org/C182462393","name":"Market system","level":2,"works_count":1750,"children_count":0},{"id":"https://openalex.org/C2776349024","name":"Macromarketing","level":2,"works_count":1349,"children_count":0},{"id":"https://openalex.org/C2777605291","name":"Invisible hand","level":2,"works_count":1582,"children_count":0},{"id":"https://openalex.org/C2781161757","name":"History of economic thought","level":2,"works_count":1470,"children_count":0},{"id":"https://openalex.org/C2993114674","name":"Home market","level":2,"works_count":482,"children_count":0},{"id":"https://openalex.org/C2992455737","name":"Free enterprise","level":2,"works_count":862,"children_count":0},{"id":"https://openalex.org/C89008666","name":"Final product","level":2,"works_count":1456,"children_count":0},{"id":"https://openalex.org/C2993248174","name":"Market regulation","level":2,"works_count":1360,"children_count":0},{"id":"https://openalex.org/C2779071577","name":"Economic planning","level":2,"works_count":1656,"children_count":0},{"id":"https://openalex.org/C2781005140","name":"Occupational licensing","level":2,"works_count":589,"children_count":0},{"id":"https://openalex.org/C2984080334","name":"Market development","level":2,"works_count":4161,"children_count":0},{"id":"https://openalex.org/C2994071783","name":"Market oriented","level":2,"works_count":239,"children_count":0},{"id":"https://openalex.org/C2781378591","name":"Family economy","level":2,"works_count":867,"children_count":0},{"id":"https://openalex.org/C68513836","name":"Profit motive","level":2,"works_count":599,"children_count":0},{"id":"https://openalex.org/C196179229","name":"Economic problem","level":2,"works_count":912,"children_count":0},{"id":"https://openalex.org/C2778796853","name":"Regulated market","level":2,"works_count":24,"children_count":0}]